laegr/__init__.py
laegr/featurization/Dataset.py
laegr/featurization/Dump2Features.py
laegr/featurization/Graph.py
laegr/featurization/GraphFeatures.py
laegr/featurization/__init__.py
laegr/model/__init__.py
laegr/model/gnn/Layer.py
laegr/model/gnn/LoadData.py
laegr/model/gnn/Model.py
laegr/model/gnn/TrainingValidation.py
laegr/model/gnn/__init__.py
laegr/model/gnn/main.py
laegr-1.1.dist-info/LICENSE
laegr-1.1.dist-info/METADATA
laegr-1.1.dist-info/WHEEL
laegr-1.1.dist-info/top_level.txt
laegr-1.1.dist-info/RECORD
